algotrade/__init__.py
algotrade/alerts.py
algotrade/calculations.py
algotrade/general.py
algotrade/ploting.py
algotrade/screener.py
algotrade/strategies.py
algotrade/testing.py
algotrade-0.1.2.dist-info/LICENSE
algotrade-0.1.2.dist-info/METADATA
algotrade-0.1.2.dist-info/WHEEL
algotrade-0.1.2.dist-info/top_level.txt
algotrade-0.1.2.dist-info/RECORD
